aws_iot/__init__.py
aws_iot/base_shadow.py
aws_iot/handler/__init__.py
aws_iot/handler/_iot_client.py
aws_iot/handler/_iot_data_client.py
aws_iot/handler/handler.py
aws_iot/handler/job_handler.py
aws_iot/handler/job_resource.py
aws_iot/handler/resource.py
aws_iot/handler/shadow_handler.py
aws_iot/handler/shadow_resource.py
aws_iot/testing/__init__.py
aws_iot/testing/fixture.py
aws_iot/testing/mock.py
aws_iot/thing/__init__.py
aws_iot/thing/connector.py
aws_iot/thing/job.py
aws_iot/thing/shadow.py
aws_iot/thing/thing.py
aws_iot-0.4.0.dist-info/LICENSE
aws_iot-0.4.0.dist-info/METADATA
aws_iot-0.4.0.dist-info/WHEEL
aws_iot-0.4.0.dist-info/top_level.txt
aws_iot-0.4.0.dist-info/RECORD
