Metadata-Version: 2.1
Name: aws-iot
Version: 0.4.0
Summary: easing interaction with AWS IoT
Home-page: UNKNOWN
Author: Jan Lukas Braje
Author-email: aws_iot@getkahawa.com
License: UNKNOWN
Platform: UNKNOWN
Classifier: Development Status :: 3 - Alpha
Classifier: Intended Audience :: Information Technology
Classifier: License :: OSI Approved :: Apache Software License
Classifier: Operating System :: OS Independent
Classifier: Programming Language :: Python :: 3.8
Requires-Python: >=3.8
Requires-Dist: boto3
Requires-Dist: AWSIoTPythonSDK
